torchelper/__init__.py
torchelper/train.py
torchelper/archs/__init__.py
torchelper/archs/inception.py
torchelper/archs/inception_bak.py
torchelper/archs/style_gan.py
torchelper/archs/vgg_19.py
torchelper/callbacks/__init__.py
torchelper/callbacks/callback.py
torchelper/callbacks/ckpt_callback.py
torchelper/callbacks/reduce_lr_on_plateau.py
torchelper/data/__init__.py
torchelper/data/base_dataset.py
torchelper/data/data_augment.py
torchelper/data/diffjpeg.py
torchelper/data/dir_dataset.py
torchelper/data/img_process.py
torchelper/events/__init__.py
torchelper/events/event.py
torchelper/events/event_center.py
torchelper/events/pbar_receiver.py
torchelper/events/receiver.py
torchelper/events/tensorboard_receiver.py
torchelper/events/wechat_receiver.py
torchelper/metrics/__init__.py
torchelper/metrics/fid.py
torchelper/metrics/lpips.py
torchelper/metrics/measure.py
torchelper/metrics/psnr.py
torchelper/metrics/ssim.py
torchelper/models/__init__.py
torchelper/models/base_model.py
torchelper/models/group_model.py
torchelper/models/lr_scheduler.py
torchelper/models/model_builder.py
torchelper/models/omgd_distiller.py
torchelper/models/trainable.py
torchelper/ops/__init__.py
torchelper/ops/fused_act/__init__.py
torchelper/ops/fused_act/fused_act.py
torchelper/ops/upfirdn2d/__init__.py
torchelper/ops/upfirdn2d/upfirdn2d.py
torchelper/utils/__init__.py
torchelper/utils/cls_utils.py
torchelper/utils/config.py
torchelper/utils/dist_util.py
torchelper/utils/global_data.py
torchelper/utils/logger.py
torchelper-0.1.11.dist-info/LICENSE
torchelper-0.1.11.dist-info/METADATA
torchelper-0.1.11.dist-info/WHEEL
torchelper-0.1.11.dist-info/top_level.txt
torchelper-0.1.11.dist-info/RECORD
